lingkar33423320/__init__.py
lingkar33423320/luaslingkar.py
lingkar33423320-0.0.2.dist-info/LICENSE
lingkar33423320-0.0.2.dist-info/METADATA
lingkar33423320-0.0.2.dist-info/WHEEL
lingkar33423320-0.0.2.dist-info/top_level.txt
lingkar33423320-0.0.2.dist-info/RECORD
