Metadata-Version: 2.1
Name: lingkar33423320
Version: 0.0.2
Summary: LUAS LINGKARAN
Home-page: https://github.com/rizalfarhan
Author: rizalfarhann
Author-email: rizalfarhannanda@gmail.com
License: MIT
Keywords: Hello
Platform: UNKNOWN
Classifier: Development Status :: 1 - Planning
